[
{"Name":"あさりメンタルクリニック","Jusho":"佐賀県佐賀市水ケ江1丁目1番7号","kouzui":"<a href='tel:0952-24-6566'>0952-24-6566</a>","gake":"<a href='' target='_blank'></a>","takashio":"×","jishin":"〇","tsunami":"精神科","kaji":"肥前精神医療センター(佐賀県神崎郡吉野ヶ里町三津160)","naisui":"","kazan":""},
{"Name":"医療法人えとう内科・循環器内科","Jusho":"佐賀県佐賀市神野東4丁目3-19","kouzui":"<a href='tel:0952-33-8177'>0952-33-8177</a>","gake":"<a href='http://etonaika.com/' target='_blank'>http://etonaika.com/</a>","takashio":"×","jishin":"〇","tsunami":"内科循環器科","kaji":"佐賀県医療センター好生館（佐賀県佐賀市嘉瀬町中原400）佐賀大学医学部附属病院（佐賀県佐賀市鍋島5丁目1-1）","naisui":"","kazan":""}
,
{"Name":"こが内科こどもクリニック","Jusho":"佐賀県佐賀市西与賀町厘外859-15","kouzui":"<a href='tel:0952-24-0541'>0952-24-0541</a>","gake":"<a href='' target='_blank'></a>","takashio":"〇","jishin":"〇","tsunami":"内科小児科","kaji":"県立医療センター好生館","naisui":"","kazan":""}
,
{"Name":"佐賀県医療センター好生館","Jusho":"佐賀県佐賀市嘉瀬町大字中原400番地","kouzui":"<a href='tel:0952-24-2171'>0952-24-2171</a>","gake":"<a href='http://www.koseikan.jp/' target='_blank'>http://www.koseikan.jp/</a>","takashio":"×","jishin":"〇","tsunami":"全科","kaji":"","naisui":"","kazan":""}
,
{"Name":"佐賀市立国民健康保険三瀬診療所","Jusho":"佐賀県佐賀市三瀬村藤原3882番地6","kouzui":"<a href='tel:0952-56-2001'>0952-56-2001</a>","gake":"<a href='' target='_blank'></a>","takashio":"〇","jishin":"〇","tsunami":"内科小児科","kaji":"富士大和温泉病院（佐賀市富士町大字梅野1721-1）佐賀大学医学部付属病院（佐賀市鍋島五丁目1番1号）","naisui":"","kazan":""}
,
{"Name":"さとうクリニック","Jusho":"佐賀県佐賀市川副町南里372-1","kouzui":"<a href='tel:0952-45-8000'>0952-45-8000</a>","gake":"<a href='https://satohclinic.jp/' target='_blank'>https://satohclinic.jp/</a>","takashio":"〇","jishin":"〇","tsunami":"内科","kaji":"","naisui":"","kazan":""}
,
{"Name":"すこやか女性クリニック","Jusho":"佐賀県佐賀市白山2-7-1エスプラッツ2F","kouzui":"<a href='tel:0952?20?1671'>0952?20?1671</a>","gake":"<a href='http://sukoyaka-jyosei.p2.weblife.me' target='_blank'>http://sukoyaka-jyosei.p2.weblife.me</a>","takashio":"×","jishin":"〇","tsunami":"婦人科","kaji":"なし","naisui":"","kazan":""}
,
{"Name":"独立行政法人国立病院機構佐賀病院","Jusho":"佐賀県佐賀市日の出1丁目20-1","kouzui":"<a href='tel:0952-30-7141'>0952-30-7141</a>","gake":"<a href='http://saga.hosp.go.jp/' target='_blank'>http://saga.hosp.go.jp/</a>","takashio":"×","jishin":"〇","tsunami":"内科循環器内科小児科外科整形外科形成外科皮膚科泌尿器科産婦人科眼科耳鼻咽喉科脳神経外科","kaji":"","naisui":"","kazan":""}
,
{"Name":"橋野こどもクリニック","Jusho":"佐賀県佐賀市高木瀬東4丁目14-3","kouzui":"<a href='tel:0952-31-0020'>0952-31-0020</a>","gake":"<a href='https://www.hashino-kodomo.comhttps://park.paa.jp/park2/clinics/1260/businesses/01' target='_blank'>https://www.hashino-kodomo.comhttps://park.paa.jp/park2/clinics/1260/businesses/01</a>","takashio":"〇","jishin":"〇","tsunami":"小児科","kaji":"佐賀県医療センター好生館（佐賀県佐賀市嘉瀬町中原400）国立病院機構佐賀病院（佐賀県佐賀市日の出1丁目20-1）佐賀大学医学部附属病院（佐賀県佐賀市鍋島5丁目1-1）","naisui":"","kazan":""}
,
{"Name":"ひさとみ内科クリニック","Jusho":"佐賀県佐賀市鍋島3丁目6-13","kouzui":"<a href='tel:0952-36-8426'>0952-36-8426</a>","gake":"<a href='https://www.qq.pref.saga.jp/pb_md_index/pb_md_list/pb_md_info/766?fileout=1' target='_blank'>https://www.qq.pref.saga.jp/pb_md_index/pb_md_list/pb_md_info/766?fileout=1</a>","takashio":"×","jishin":"〇","tsunami":"内科糖尿病内科","kaji":"佐賀大学医学部附属病院佐賀県医療センター好生館","naisui":"","kazan":""}
,
{"Name":"ひさのう循環器・内科","Jusho":"佐賀県佐賀市鍋島1丁目5-1","kouzui":"<a href='tel:0952-33-0020'>0952-33-0020</a>","gake":"<a href='' target='_blank'></a>","takashio":"×","jishin":"〇","tsunami":"循環器内科内科","kaji":"","naisui":"","kazan":""}
,
{"Name":"ぶどうの木クリニック","Jusho":"佐賀県佐賀市水ケ江1丁目2-21","kouzui":"<a href='tel:0952-20-0899'>0952-20-0899</a>","gake":"<a href='http://budounoki-mc.jp/' target='_blank'>http://budounoki-mc.jp/</a>","takashio":"〇","jishin":"〇","tsunami":"内科","kaji":"佐賀大学附属病院（佐賀県佐賀市鍋島5-1-1）好生館（佐賀市嘉瀬町大字中原400）国立病院機構佐賀病院（佐賀県佐賀市日の出1-20-1）","naisui":"","kazan":""}
,
{"Name":"美川眼科医院","Jusho":"佐賀県佐賀市松原四丁目3番21号","kouzui":"<a href='tel:0952-23-2789'>0952-23-2789</a>","gake":"<a href='http://www.yt-eyeclinic.or.jp/mikawa' target='_blank'>http://www.yt-eyeclinic.or.jp/mikawa</a>","takashio":"〇","jishin":"〇","tsunami":"眼科","kaji":"美川眼科医院","naisui":"","kazan":""}
,
{"Name":"満岡内科クリニック","Jusho":"佐賀県佐賀市大和町大字尼寺848番地11","kouzui":"<a href='tel:0952-51-2922'>0952-51-2922</a>","gake":"<a href='http://www.areahot.jp/saga/mitsuoka' target='_blank'>http://www.areahot.jp/saga/mitsuoka</a>","takashio":"〇","jishin":"〇","tsunami":"内科消化器科","kaji":"国立病院機構佐賀病院（佐賀県佐賀市日の出1丁目20-1）","naisui":"","kazan":""}
,
{"Name":"みね内科循環器科クリニック","Jusho":"佐賀県佐賀市高木瀬町大字東高木231-12","kouzui":"<a href='tel:0952-37-3986'>0952-37-3986</a>","gake":"<a href='http://mine-cl.jp' target='_blank'>http://mine-cl.jp</a>","takashio":"〇","jishin":"〇","tsunami":"内科","kaji":"国立病院機構佐賀病院（佐賀県佐賀市日の出1丁目20-1）","naisui":"","kazan":""}
,
{"Name":"やさか内科皮膚科","Jusho":"佐賀県佐賀市木原一丁目24番38号","kouzui":"<a href='tel:0952-29-1722'>0952-29-1722</a>","gake":"<a href='' target='_blank'></a>","takashio":"〇","jishin":"〇","tsunami":"内科、皮膚科","kaji":"諸隈病院（佐賀市水ケ江2-6-22）","naisui":"","kazan":""}
,
{"Name":"医療法人希清会岩本内科","Jusho":"佐賀県唐津市海岸通7182-306","kouzui":"<a href='tel:0955-72-2877'>0955-72-2877</a>","gake":"<a href='' target='_blank'></a>","takashio":"〇","jishin":"〇","tsunami":"内科","kaji":"唐津赤十字病院（佐賀県唐津市和多田2430）","naisui":"","kazan":""}
,
{"Name":"医療法人桑原医院","Jusho":"佐賀県唐津市浜玉町浜崎1067-1","kouzui":"<a href='tel:0955-56-8761'>0955-56-8761</a>","gake":"<a href='' target='_blank'></a>","takashio":"〇","jishin":"〇","tsunami":"内科□小児科","kaji":"唐津東松浦医師会医療センター(佐賀県唐津市千代田町2566-11）","naisui":"","kazan":""}
,
{"Name":"医療法人修腎会藤崎病院","Jusho":"佐賀県唐津市栄町2576番地9","kouzui":"<a href='tel:0955-72-5125'>0955-72-5125</a>","gake":"<a href='' target='_blank'></a>","takashio":"×","jishin":"〇","tsunami":"皮膚科泌尿器科内科","kaji":"栄町クリニック□佐賀県唐津市栄町2588番地17","naisui":"","kazan":""}
,
{"Name":"医療法人春陽会野口内科","Jusho":"佐賀県唐津市大名小路2-44","kouzui":"<a href='tel:0955-72-2314'>0955-72-2314</a>","gake":"<a href='https://byoinnavi.jp/clinic/100482' target='_blank'>https://byoinnavi.jp/clinic/100482</a>","takashio":"〇","jishin":"〇","tsunami":"内科糖尿病内科","kaji":"唐津赤十字病院（佐賀県唐津市和多田2430）唐津済生会病院（佐賀県唐津市元旗町817）","naisui":"","kazan":""}
,
{"Name":"医療法人心和会藤原外科医院","Jusho":"佐賀県唐津市朝日町988番地1","kouzui":"<a href='tel:0955-72-4747'>0955-72-4747</a>","gake":"<a href='' target='_blank'></a>","takashio":"〇","jishin":"〇","tsunami":"内科","kaji":"唐津赤十字病院（佐賀県唐津市和多田2430番地）","naisui":"","kazan":""}
,
{"Name":"医療法人慈孝会七山診療所","Jusho":"佐賀県唐津市七山藤川2755-6","kouzui":"<a href='tel:0955-58-3003'>0955-58-3003</a>","gake":"<a href='' target='_blank'></a>","takashio":"〇","jishin":"〇","tsunami":"内科外科","kaji":"唐津赤十字病院（唐津市和多田2430）済生会唐津病院（唐津市元旗町817）","naisui":"","kazan":""}
,
{"Name":"医療法人整和会副島整形外科病院","Jusho":"佐賀県唐津市和多田天満町一丁目2番1号","kouzui":"<a href='tel:0955-72-8335'>0955-72-8335</a>","gake":"<a href='http://seiwakai-karatsu.or.jp/' target='_blank'>http://seiwakai-karatsu.or.jp/</a>","takashio":"〇","jishin":"〇","tsunami":"整形外科","kaji":"","naisui":"","kazan":""}
,
{"Name":"医療法人整和会副島整形外科クリニック","Jusho":"佐賀県唐津市和多田天満町一丁目2番1号","kouzui":"<a href='tel:0955-72-8335'>0955-72-8335</a>","gake":"<a href='http://seiwakai-karatsu.or.jp/' target='_blank'>http://seiwakai-karatsu.or.jp/</a>","takashio":"〇","jishin":"〇","tsunami":"整形外科","kaji":"","naisui":"","kazan":""}
,
{"Name":"医療法人平川病院","Jusho":"佐賀県唐津市山本644番地5","kouzui":"<a href='tel:0955-78-0026'>0955-78-0026</a>","gake":"<a href='http://www.hp-hirakawa.com/' target='_blank'>http://www.hp-hirakawa.com/</a>","takashio":"〇","jishin":"〇","tsunami":"外科内科ペインクリニック外科","kaji":"唐津赤十字病院（佐賀県唐津市和多田2430）","naisui":"","kazan":""}
,
{"Name":"井本整形外科内科クリニック","Jusho":"佐賀県唐津市東城内17-26","kouzui":"<a href='tel:0955-74-8700'>0955-74-8700</a>","gake":"<a href='https://itp.ne.jp/info/411552279400000899/' target='_blank'>https://itp.ne.jp/info/411552279400000899/</a>","takashio":"〇","jishin":"〇","tsunami":"整形外科・内科","kaji":"済生会唐津病院（佐賀県唐津市元旗町）","naisui":"","kazan":""}
,
{"Name":"加藤眼科医院","Jusho":"佐賀県唐津市西城内6-43","kouzui":"<a href='tel:0955-72-2009'>0955-72-2009</a>","gake":"<a href='' target='_blank'></a>","takashio":"〇","jishin":"〇","tsunami":"眼科","kaji":"当院にて","naisui":"","kazan":""}
,
{"Name":"河畔病院","Jusho":"佐賀県唐津市松南町119番地2","kouzui":"<a href='tel:0955-77-2611'>0955-77-2611</a>","gake":"<a href='http://www.shouraikai.jp/kahan/' target='_blank'>http://www.shouraikai.jp/kahan/</a>","takashio":"×","jishin":"〇","tsunami":"内科外科脳神経外科脳神経内科整形外科消化器内科循環器内科呼吸器内科緩和ケア内科糖尿病内科","kaji":"当院にて","naisui":"","kazan":""}
,
{"Name":"唐津市民病院きたはた","Jusho":"佐賀県唐津市北波多徳須恵1424-1","kouzui":"<a href='tel:0955-64-2611'>0955-64-2611</a>","gake":"<a href='https://www.city.karatsu.lg.jp/kenko/kenko/iryo/kitahata/index.html' target='_blank'>https://www.city.karatsu.lg.jp/kenko/kenko/iryo/kitahata/index.html</a>","takashio":"×","jishin":"〇","tsunami":"内科","kaji":"","naisui":"","kazan":""}
,
{"Name":"唐津赤十字病院","Jusho":"佐賀県唐津市和多田2430","kouzui":"<a href='tel:0955-72-5111'>0955-72-5111</a>","gake":"<a href='http://www.karatsu.jrc.or.jp' target='_blank'>http://www.karatsu.jrc.or.jp</a>","takashio":"×","jishin":"〇","tsunami":"内科小児科脳神経外科","kaji":"","naisui":"","kazan":""}
,
{"Name":"酒井医院","Jusho":"佐賀県唐津市大名小路5-3","kouzui":"<a href='tel:0955-72-5445'>0955-72-5445</a>","gake":"<a href='http://nagomikai.egoism.jp/' target='_blank'>http://nagomikai.egoism.jp/</a>","takashio":"〇","jishin":"〇","tsunami":"内科外科胃腸科リハビリテーション科","kaji":"唐津赤十字病院（佐賀県唐津市和多田2430）済生会唐津病院（佐賀県唐津市元旗町817）医師会医療センター（佐賀県唐津市千代田町2566-11）","naisui":"","kazan":""}
,
{"Name":"城内病院","Jusho":"佐賀県唐津市南城内2-17","kouzui":"<a href='tel:0955-79-8550'>0955-79-8550</a>","gake":"<a href='https://jyonai-hp.sankenkai.or.jp/' target='_blank'>https://jyonai-hp.sankenkai.or.jp/</a>","takashio":"×","jishin":"〇","tsunami":"内科","kaji":"","naisui":"","kazan":""}
,
{"Name":"新屋敷病院","Jusho":"佐賀県唐津市相知町町切898-3","kouzui":"<a href='tel:0955-63-3131'>0955-63-3131</a>","gake":"<a href='' target='_blank'></a>","takashio":"〇","jishin":"〇","tsunami":"内科","kaji":"唐津赤十字病院（佐賀県唐津市和多田2430）","naisui":"","kazan":""}
,
{"Name":"たじまメンタルクリニック","Jusho":"佐賀県唐津市町田2丁目4-6","kouzui":"<a href='tel:0955-79-9087'>0955-79-9087</a>","gake":"<a href='https://tajima-mentalclinic.com/' target='_blank'>https://tajima-mentalclinic.com/</a>","takashio":"×","jishin":"〇","tsunami":"精神科心療内科","kaji":"なし","naisui":"","kazan":""}
,
{"Name":"長生堂渡辺医院","Jusho":"唐津市海岸通7182-58","kouzui":"<a href='tel:0955-72-2770'>0955-72-2770</a>","gake":"<a href='' target='_blank'></a>","takashio":"〇","jishin":"〇","tsunami":"内科小児科","kaji":"済生会唐津病院","naisui":"","kazan":""}
,
{"Name":"夏秋レディースクリニック","Jusho":"唐津市南城内2-8","kouzui":"<a href='tel:0955-75-0840'>0955-75-0840</a>","gake":"<a href='' target='_blank'></a>","takashio":"〇","jishin":"〇","tsunami":"婦人科内科","kaji":"唐津赤十字病院","naisui":"","kazan":""}
,
{"Name":"虹と海のホスピタル","Jusho":"佐賀県唐津市原842番地1","kouzui":"<a href='tel:0955-77-0711'>0955-77-0711</a>","gake":"<a href='http://www.nijitoumi.or.jp/' target='_blank'>http://www.nijitoumi.or.jp/</a>","takashio":"×","jishin":"〇","tsunami":"内科・精神科","kaji":"なし","naisui":"","kazan":""}
,
{"Name":"藤松内科医院","Jusho":"佐賀県唐津市西城内6番4号","kouzui":"<a href='tel:0955-72-2616'>0955-72-2616</a>","gake":"<a href='http://www.surp2.net/~fujimats-clinic/index.html' target='_blank'>http://www.surp2.net/~fujimats-clinic/index.html</a>","takashio":"〇","jishin":"〇","tsunami":"内科","kaji":"唐津赤十字病院（佐賀県唐津市和多田2430）済生会唐津病院（佐賀県唐津市元旗町817）","naisui":"","kazan":""}
,
{"Name":"冬野医院","Jusho":"佐賀県唐津市西城内5-12","kouzui":"<a href='tel:0955-72-2905'>0955-72-2905</a>","gake":"<a href='' target='_blank'></a>","takashio":"〇","jishin":"〇","tsunami":"内科","kaji":"唐津赤十字病院（佐賀県唐津市和多田2430）","naisui":"","kazan":""}
,
{"Name":"宮崎外科胃腸科","Jusho":"佐賀県唐津市新興町68番地","kouzui":"<a href='tel:0955-72-8115'>0955-72-8115</a>","gake":"<a href='' target='_blank'></a>","takashio":"×","jishin":"〇","tsunami":"外科胃腸科","kaji":"唐津赤十字病院（佐賀県唐津市和多田2430）済生会唐津病院（佐賀県唐津市元旗町817）","naisui":"","kazan":""}
,
{"Name":"山下町クリニック","Jusho":"佐賀県唐津市山下町1141-2","kouzui":"<a href='tel:0955-72-4478'>0955-72-4478</a>","gake":"<a href='' target='_blank'></a>","takashio":"×","jishin":"〇","tsunami":"内科","kaji":"","naisui":"","kazan":""}
,
{"Name":"悠悠クリニック","Jusho":"佐賀県唐津市鏡2537番地","kouzui":"<a href='tel:0955-77-0949'>0955-77-0949</a>","gake":"<a href='http://you-youclinic.org/' target='_blank'>http://you-youclinic.org/</a>","takashio":"〇","jishin":"〇","tsunami":"内科","kaji":"唐津赤十字病院（佐賀県唐津市和多田2430）済生会唐津病院（佐賀県唐津市元旗町817）","naisui":"","kazan":""}
,
{"Name":"渡辺内科","Jusho":"佐賀県唐津市肥前町入野丙915-7","kouzui":"<a href='tel:0955-54-0016'>0955-54-0016</a>","gake":"<a href='' target='_blank'></a>","takashio":"×","jishin":"〇","tsunami":"内科","kaji":"","naisui":"","kazan":""}
,
{"Name":"医療法人梅野耳鼻咽喉科","Jusho":"佐賀県鳥栖市本町1丁目924番地1","kouzui":"<a href='tel:0942-82-2318'>0942-82-2318</a>","gake":"<a href='' target='_blank'></a>","takashio":"〇","jishin":"〇","tsunami":"耳鼻咽喉科","kaji":"久留米大学病院","naisui":"","kazan":""}
,
{"Name":"医療法人せとじまクリニック","Jusho":"佐賀県鳥栖市真木町1974-4","kouzui":"<a href='tel:0942-87-5008'>0942-87-5008</a>","gake":"<a href='http://setojima-clinic.com' target='_blank'>http://setojima-clinic.com</a>","takashio":"〇","jishin":"〇","tsunami":"内科外科","kaji":"やよいがおか鹿毛病院(鳥栖市弥生が丘2丁目143）聖マリア病院（久留米市津福本町422番地）","naisui":"","kazan":""}
,
{"Name":"医療法人まごころ医療館","Jusho":"佐賀県鳥栖市蔵上2丁目210番地","kouzui":"<a href='tel:0942-87-5002'>0942-87-5002</a>","gake":"<a href='http://magokoroiryoukan.com/' target='_blank'>http://magokoroiryoukan.com/</a>","takashio":"〇","jishin":"〇","tsunami":"内科・整形外科","kaji":"医療法人社団如水会今村病院","naisui":"","kazan":""}
,
{"Name":"医療法人むらかみ小児科","Jusho":"佐賀県鳥栖市古野町190-10","kouzui":"<a href='tel:0942-83-2450'>0942-83-2450</a>","gake":"<a href='' target='_blank'></a>","takashio":"〇","jishin":"〇","tsunami":"小児科","kaji":"聖マリア病院（福岡県久留米市）","naisui":"","kazan":""}
,
{"Name":"大園内科医院","Jusho":"佐賀県鳥栖市萱方町158-10","kouzui":"<a href='tel:0942-87-8888'>0942-87-8888</a>","gake":"<a href='http://www.oozono.co.jp' target='_blank'>http://www.oozono.co.jp</a>","takashio":"〇","jishin":"〇","tsunami":"内科","kaji":"やよいがおか鹿毛病院（佐賀県鳥栖市弥生が丘2-143)今村病院（佐賀県鳥栖市轟木町1523-6）","naisui":"","kazan":""}
,
{"Name":"すむのさと髙尾病院","Jusho":"佐賀県鳥栖市高田町210-1","kouzui":"<a href='tel:0942-84-8838'>0942-84-8838</a>","gake":"<a href='http://www.koukodou.or.jp/' target='_blank'>http://www.koukodou.or.jp/</a>","takashio":"×","jishin":"〇","tsunami":"内科","kaji":"","naisui":"","kazan":""}
,
{"Name":"伊万里整形外科病院","Jusho":"佐賀県伊万里市木須町4450番地","kouzui":"<a href='tel:0955-23-2504'>0955-23-2504</a>","gake":"<a href='https://imari-orthopedics-hospital.jimdosite.com/' target='_blank'>https://imari-orthopedics-hospital.jimdosite.com/</a>","takashio":"〇","jishin":"〇","tsunami":"整形外科","kaji":"伊万里有田共立病院（佐賀県西松浦郡有田町二ノ瀬甲860番地）","naisui":"","kazan":""}
,
{"Name":"伊万里篠田皮ふ科・形成外科","Jusho":"佐賀県伊万里市新天町460番地11","kouzui":"<a href='tel:0955-21-1001'>0955-21-1001</a>","gake":"<a href='http://www.imari-hifuka.com' target='_blank'>http://www.imari-hifuka.com</a>","takashio":"〇","jishin":"〇","tsunami":"皮膚科形成外科","kaji":"佐賀大学医学部附属病院佐賀市鍋島五丁目1番1号国立病院機構佐賀病院佐賀市日の出一丁目20-1佐賀県医療センター好生館佐賀市嘉瀬町大字中原400嬉野医療センター嬉野町大字下宿甲4279-3伊万里有田共立病院有田町二ノ瀬甲860番地佐世保総合医療センター佐世保市平瀬町9-3","naisui":"","kazan":""}
,
{"Name":"医療法人たけお内科医院","Jusho":"佐賀県武雄市武雄町大字昭和11-2","kouzui":"<a href='tel:0954-23-4988'>0954-23-4988</a>","gake":"<a href='http://www2.saganet.ne.jp/neuron' target='_blank'>http://www2.saganet.ne.jp/neuron</a>","takashio":"×","jishin":"〇","tsunami":"内科","kaji":"","naisui":"","kazan":""}
,
{"Name":"くさの耳鼻咽喉科・小児科","Jusho":"佐賀県武雄市朝日町大字甘久1287","kouzui":"<a href='tel:0954-23-3333'>0954-23-3333</a>","gake":"<a href='https://www.kusano-jibika.com/' target='_blank'>https://www.kusano-jibika.com/</a>","takashio":"〇","jishin":"〇","tsunami":"耳鼻咽喉科小児科","kaji":"新武雄病院嬉野医療センター","naisui":"","kazan":""}
,
{"Name":"古賀内科医院","Jusho":"佐賀県武雄市武雄町大字富岡11534-2","kouzui":"<a href='tel:0954-22-3135'>0954-22-3135</a>","gake":"<a href='' target='_blank'></a>","takashio":"×","jishin":"〇","tsunami":"内科□","kaji":"嬉野医療センター〒佐賀県嬉野市嬉野町下宿甲4279-3","naisui":"","kazan":""}
,
{"Name":"篠田皮ふ科・形成外科","Jusho":"佐賀県武雄市武雄町大字昭和106番地","kouzui":"<a href='tel:0954-23-1240'>0954-23-1240</a>","gake":"<a href='http://www.shinoda-hifuka.com' target='_blank'>http://www.shinoda-hifuka.com</a>","takashio":"〇","jishin":"〇","tsunami":"皮膚科形成外科","kaji":"佐賀大学医学部附属病院佐賀市鍋島五丁目1番1号国立病院機構佐賀病院佐賀市日の出一丁目20-1佐賀県医療センター好生館佐賀市嘉瀬町大字中原400嬉野医療センター嬉野町大字下宿甲4279-3新武雄病院武雄市武雄町富岡12628番地","naisui":"","kazan":""}
,
{"Name":"竜門堂医院","Jusho":"佐賀県武雄市山内町大字大野6602番地1","kouzui":"<a href='tel:0954-20-7050'>0954-20-7050</a>","gake":"<a href='http://www.ryumondo.or.jp' target='_blank'>http://www.ryumondo.or.jp</a>","takashio":"〇","jishin":"〇","tsunami":"内科","kaji":"","naisui":"","kazan":""}
,
{"Name":"医療法人社団別府整形外科","Jusho":"佐賀県鹿島市大字高津原3523の1","kouzui":"<a href='tel:0954-63-3063'>0954-63-3063</a>","gake":"<a href='http://www.beppu-seikei.jp/' target='_blank'>http://www.beppu-seikei.jp/</a>","takashio":"〇","jishin":"〇","tsunami":"整形外科","kaji":"織田病院（佐賀県鹿島市高津原4306）嬉野医療センター（佐賀県嬉野市嬉野町大字下宿甲4279-3）","naisui":"","kazan":""}
,
{"Name":"独立行政法人国立病院機構嬉野医療センター","Jusho":"佐賀県嬉野市嬉野町大字下宿甲4279番地3","kouzui":"<a href='tel:0954-43-1120'>0954-43-1120</a>","gake":"<a href='https://ureshino.hosp.go.jp/' target='_blank'>https://ureshino.hosp.go.jp/</a>","takashio":"×","jishin":"〇","tsunami":"全診療科","kaji":"","naisui":"","kazan":""}
,
{"Name":"医療法人山田こどもクリニック","Jusho":"佐賀県神埼市神埼町田道ケ里2394-1","kouzui":"<a href='tel:0952-55-6566'>0952-55-6566</a>","gake":"<a href='' target='_blank'></a>","takashio":"〇","jishin":"〇","tsunami":"小児科","kaji":"佐賀県医療センター好生館（佐賀市嘉瀬町大字中原400）佐賀大学医学部附属病院（佐賀市鍋島五丁目1番1号）","naisui":"","kazan":""}
,
{"Name":"神埼病院","Jusho":"佐賀県神埼市神埼町田道ケ里2216-1","kouzui":"<a href='tel:0952-52-3145'>0952-52-3145</a>","gake":"<a href='http://hosp-kan.webmedipr.jp/' target='_blank'>http://hosp-kan.webmedipr.jp/</a>","takashio":"〇","jishin":"〇","tsunami":"内科","kaji":"好生館（佐賀県嘉瀬町大字中原400）東佐賀病院（佐賀県三養基郡みやき町大字原古賀7324）","naisui":"","kazan":""}
,
{"Name":"しらいし内科","Jusho":"佐賀県神埼市神埼町城原1256-1","kouzui":"<a href='tel:0952-52-3848'>0952-52-3848</a>","gake":"<a href='' target='_blank'></a>","takashio":"〇","jishin":"〇","tsunami":"内科","kaji":"橋本病院（神埼市神埼町本告牟田3005）神埼病院(神埼市神埼町田道ケ里2216-1）佐賀中部病院（佐賀市兵庫南3-8-1）東佐賀病院（三養基郡みやき町大字原古賀7324）","naisui":"","kazan":""}
,
{"Name":"中下医院","Jusho":"佐賀県神埼市千代田町餘江128番地","kouzui":"<a href='tel:0952-44-2488'>0952-44-2488</a>","gake":"<a href='' target='_blank'></a>","takashio":"〇","jishin":"〇","tsunami":"内科","kaji":"佐賀県医療センター好生館（佐賀県佐賀市嘉瀬町中原400）","naisui":"","kazan":""}
,
{"Name":"松本医院","Jusho":"佐賀県神埼郡吉野ヶ里町三津751-9","kouzui":"<a href='tel:0952-52-4185'>0952-52-4185</a>","gake":"<a href='' target='_blank'></a>","takashio":"×","jishin":"〇","tsunami":"内科小児科消化器科リウマチ科","kaji":"独立行政法人国立病院機構東佐賀病院（佐賀県三養基郡みやき町大字原古賀7324）","naisui":"","kazan":""}
,
{"Name":"医療法人）さかい胃腸・内視鏡内科クリニック","Jusho":"佐賀県三養基郡基山町小倉1059-2","kouzui":"<a href='tel:0942-92-1121'>0942-92-1121</a>","gake":"<a href='https://www.kiyama-naishikyou.jp/' target='_blank'>https://www.kiyama-naishikyou.jp/</a>","takashio":"〇","jishin":"〇","tsunami":"内科","kaji":"嶋田病院（福岡県小郡市）鹿毛病院（佐賀県三養基郡基山町）二日市済生会（福岡県二日市市）","naisui":"","kazan":""}
,
{"Name":"医療法人田渕医院","Jusho":"佐賀県東松浦郡玄海町大字諸浦6番地1","kouzui":"<a href='tel:0955-52-2311'>0955-52-2311</a>","gake":"<a href='' target='_blank'></a>","takashio":"×","jishin":"〇","tsunami":"内科□","kaji":"唐津赤十字病院（佐賀県唐津市和多田2430番地）","naisui":"","kazan":""}
,
{"Name":"順天堂病院","Jusho":"佐賀県杵島郡大町町大字福母707番地2","kouzui":"<a href='tel:0952-82-3161'>0952-82-3161</a>","gake":"<a href='http://juntendo.or.jp' target='_blank'>http://juntendo.or.jp</a>","takashio":"〇","jishin":"〇","tsunami":"内科脳外科整形外科","kaji":"新武雄病院（佐賀県武雄市武雄町大字富岡12628）白石共立病院（佐賀県杵島郡白石町大字福田1296）","naisui":"","kazan":""}
,
{"Name":"白石共立病院","Jusho":"佐賀県杵島郡白石町大字福田1296","kouzui":"<a href='tel:0952-84-6060'>0952-84-6060</a>","gake":"<a href='http://shiroishikyouritsu.jp/' target='_blank'>http://shiroishikyouritsu.jp/</a>","takashio":"×","jishin":"〇","tsunami":"全診療科(疾患により対応不可の場合あり)","kaji":"白石共立病院(佐賀県杵島郡白石町大字福田1296)","naisui":"","kazan":""}
,
{"Name":"原田内科医院","Jusho":"佐賀県杵島郡白石町大字福富1827","kouzui":"<a href='tel:0952-87-3737'>0952-87-3737</a>","gake":"<a href='' target='_blank'></a>","takashio":"〇","jishin":"〇","tsunami":"内科胃腸科消化器科","kaji":"佐賀県医療センター好生館佐賀県佐賀市嘉瀬町中原400","naisui":"","kazan":""}
]